RAZDEL_CAT/__INIT__.py
RAZDEL_CAT/main.py
RAZDEL_CAT-0.0.1.dist-info/LICENSE
RAZDEL_CAT-0.0.1.dist-info/METADATA
RAZDEL_CAT-0.0.1.dist-info/WHEEL
RAZDEL_CAT-0.0.1.dist-info/top_level.txt
RAZDEL_CAT-0.0.1.dist-info/RECORD
